kaiju_mqtt_py/__init__.py
kaiju_mqtt_py/__version__.py
kaiju_mqtt_py/kaiju_mqtt_py.py
kaiju_mqtt_py/mqtt_enum.py
kaiju_mqtt_py/topicmaker.py
kaiju_mqtt_py-3.1.0.dist-info/METADATA
kaiju_mqtt_py-3.1.0.dist-info/WHEEL
kaiju_mqtt_py-3.1.0.dist-info/dependency_links.txt
kaiju_mqtt_py-3.1.0.dist-info/top_level.txt
kaiju_mqtt_py-3.1.0.dist-info/RECORD
