Metadata-Version: 2.1
Name: kaiju-mqtt-py
Version: 3.1.0
Summary: UNKNOWN
Home-page: UNKNOWN
Author: Netflix TSC
Author-email: davidb@netflix.com
License: UNKNOWN
Keywords: kaiju-mqtt-py
Platform: UNKNOWN
Classifier: Development Status :: 4 - Beta
Classifier: Environment :: Console
Classifier: Operating System :: OS Independent
Classifier: Programming Language :: Python
Classifier: Programming Language :: Python :: 3.6
Classifier: Programming Language :: Python :: 3 :: Only
Classifier: Topic :: Software Development :: Libraries
Classifier: Topic :: Software Development :: Testing
Requires-Python: >=3.6
Requires-Dist: paho-mqtt (==1.5.1)
Requires-Dist: requests
Requires-Dist: dataclasses ; python_version < "3.7"
Provides-Extra: test
Requires-Dist: tox ; extra == 'test'
Requires-Dist: hbmqtt (==0.9.6) ; extra == 'test'
